Mux8x1/Testbench_Mux8x1.v
/* *************************************************************************
								Proyecto de Verilog
							Universidad de Costa Rica
						Escuela de Ingenieria Electrica
						IE-0323: Circuitos Digitales I 
							
								Testbench_Mux8x1.v
								
Autores: Jafet David Gutierrez Guevara <jafet.gutierrez@ucr.ac.cr>
         Carné: B73558
		 Pablo Daniel Brenes Segura <pablo.brenessegura@ucr.ac.cr>
		 Carné: B51243
Fecha: 25/02/2021

Descripcion:
	Contiene el testbench para el modulo de un Mux 8x1
	
***************************************************************************/

/** 
* Se incluye la directiva de compilar timescale para indicar el valor
* de cada unidad de tiempo.
* Unidad: 1ns
* Precision: 1ns
**/
`timescale 1ns/1ns

/**
* Modulo de prueba en el que se aplicaran las señales de entrada
* y se observaran las respuestas del modulo Mux8x1
**/

module Testbench_Mux8x1(
	output reg [7:0][3:0] I,
	output reg [2:0] S,
	input wire [3:0] Q);

	/**
	* Los siguientes parameters serviran como entradas
	* de prueba para el Mux8x1
	**/

	parameter e0 = 4'd0;
	parameter e1 = 4'd1;
	parameter e2 = 4'd2;
	parameter e3 = 4'd3;
	parameter e4 = 4'd4;
	parameter e5 = 4'd5;
	parameter e6 = 4'd6;
	parameter e7 = 4'd7;

	/** 
	* Se dispone de un initial block para estimular todas
	* las señales especificas en una sola prueba, subdividida
	* en varias sub-pruebas
	**/
	initial
		begin

			/**
			* Se define el nombre el archivo .vcd en cual se
			* guardaran todos los valores de las nets y regs que
			* cambian en la simulacion
			**/

			$dumpfile("Mux8x1.vcd");
			$dumpvars; // Especificacion para que se guarden todas las variables en el archivo .vcd

			/**
			* Se pasan los valores de los parameters definidos
			* anteriormente a las entradas del Mux8x1
			**/
			I[0] = e0;
			I[1] = e1;
			I[2] = e2;
			I[3] = e3;
			I[4] = e4;
			I[5] = e5;
			I[6] = e6;
			I[7] = e7;

			// Pruebas para el Mux8x1

			/** 
			* Tomando las entradas de seleccion en orden de precedencia 
			* como S[2]S[1]S[0] y dejando un retardo de una unidad de
			* tiempo entre cada prueba
			**/

			//Prueba 1 - S[2]S[1]S[0] = 000
			#1
			S[2] = 0;
			S[1] = 0;
			S[0] = 0;

			//Prueba 2 - S[2]S[1]S[0] = 001
			#1
			S[2] = 0;
			S[1] = 0;
			S[0] = 1;

			//Prueba 3 - S[2]S[1]S[0] = 010
			#1
			S[2] = 0;
			S[1] = 1;
			S[0] = 0;

			//Prueba 4 - S[2]S[1]S[0] = 011
			#1
			S[2] = 0;
			S[1] = 1;
			S[0] = 1;

			//Prueba 5 - S[2]S[1]S[0] = 100
			#1
			S[2] = 1;
			S[1] = 0;
			S[0] = 0;

			//Prueba 6 - S[2]S[1]S[0] = 101
			#1
			S[2] = 1;
			S[1] = 0;
			S[0] = 1;

			//Prueba 7 - S[2]S[1]S[0] = 110
			#1
			S[2] = 1;
			S[1] = 1;
			S[0] = 0;

			//Prueba 8 - S[2]S[1]S[0] = 111
			#1
			S[2] = 1;
			S[1] = 1;
			S[0] = 1;

			/** 
			* Se da una unidad de tiempo mas para poder
			* observar los resultados de la ultima prueba
			* y se termina la simulacion con el keyword finish
			**/
			#1 $finish;
		end
endmodule

Mux8x1/Mux8x1.v
/* *************************************************************************
								Proyecto de Verilog
							Universidad de Costa Rica
						Escuela de Ingenieria Electrica
						IE-0323: Circuitos Digitales I 
							
									Mux8x1.v
								
Autores: Jafet David Gutierrez Guevara <jafet.gutierrez@ucr.ac.cr>
		 Carné: B73558
		 Pablo Daniel Brenes Segura <pablo.brenessegura@ucr.ac.cr>
		 Carné: B51243
Fecha: 25/02/2021

Descripcion:
	Contiene el modulo de un Mux 8x1 construido a partir de modulos Mux4x1,
	que a su vez estan construidos a partir de modulos Mux2x1.
	
***************************************************************************/


/**
* Mux 2x1 Estructural
**/

module Mux2x1(
	input wire [1:0][3:0] I, // Dos entradas de 4 bits
	input wire S, // Entrada de seleccion
	output wire [3:0] Q // Salida de 4 bits
	);

	/**
	* Se utiliza una asignacion condicional, con respecto a
	* la entrada de seleccion, para establecer el valor de 
	* la salida Q
	**/

assign Q = S ? I[1] : I[0]; // Si S=1 => Q=I1, si S=0 => Q=I0
endmodule

/**
* MUX 4x1 construido a partir de modulos Mux2x1
**/

module Mux4x1(
	input wire [3:0][3:0] I, // Cuantro entradas de 4 bits
	input wire [1:0] S, // Dos entradas de seleccion
	output wire [3:0] Q); // Salida de 4 bits

	/**
	* c_arriba es el cable que conecta la salida del mux_arriba con una
	* de las entradas del mux_final y c_abajo es el cable que conecta la
	* salida del mux_abajo con la otra entrada del mux_final.
	**/

	wire [3:0] c_arriba, c_abajo; 

	// Se instancian dos modulos de Mux2x1 

	Mux2x1 mux_arriba(I[1:0], S[0], c_arriba);
	Mux2x1 mux_abajo(I[3:2], S[0], c_abajo);

	// Para el mux_final: c_abajo -> I1 y c_arriba -> I0

	Mux2x1 mux_final({c_abajo, c_arriba}, S[1], Q);

endmodule

/**
* MUX 8x1 construido a partir de modulos Mux4x1
**/

module Mux8x1(
	input wire [7:0][3:0] I, // Ocho entradas de 4 bits
	input wire [2:0] S, // Tres entradas de seleccion
	output wire [3:0] Q); // Salida de 4 bits

	/**
	* c_arriba es el cable que conecta la salida del mux_arriba con una
	* de las entradas del mux_final y c_abajo es el cable que conecta la
	* salida del mux_abajo con la otra entrada del mux_final.
	**/

	wire [3:0] c_arriba, c_abajo; 

	// Se instancian dos modulos de Mux4x1 

	Mux4x1 mux_arriba(I[3:0], S[1:0], c_arriba);
	Mux4x1 mux_abajo(I[7:4], S[1:0], c_abajo);

	/**
	* Para el mux_final se hara una instancia de Mux2x1 
	* donde: c_abajo -> I1 y c_arriba -> I0
	**/

	Mux2x1 mux_final({c_abajo, c_arriba}, S[2], Q);

endmodule

Mux8x1/Probador_Mux8x1.v
/* *************************************************************************
								Proyecto de Verilog
							Universidad de Costa Rica
						Escuela de Ingenieria Electrica
						IE-0323: Circuitos Digitales I 
							
								Probador_Mux8x1.v
								
Autores: Jafet David Gutierrez Guevara <jafet.gutierrez@ucr.ac.cr>
         Carné: B73558
		 Pablo Daniel Brenes Segura <pablo.brenessegura@ucr.ac.cr>
		 Carné: B51243
Fecha: 25/02/2021

Descripcion:
	Contiene el probador que conecta al modulo Mux8x1 con su modulo de 
	testbench.
	
***************************************************************************/

/** 
* Se incluye el contenido de los archivos Mux8x1.v y Testbench_Mux8x1.v,
* los cuales contienen el modulo Mux8x1 a probar y su respectivo 
* testbench
**/
`include "Mux8x1.v"
`include "Testbench_Mux8x1.v"

/**
* Modulo probador para el Mux8x1 diseñado
**/
module Probador();

	/** 
	* Se declaran los wires que van a conectar cada una de las entradas
	* y salidas entre el modulo Mux8x1 y su testbench
	**/
	wire [7:0][3:0] I; 
	wire [2:0] S;
	wire [3:0] Q;

	/** 
	* Se instancian los modulos del Mux8x1 y su testbench,
	* y se conectan sus entradas y salidas a los correspondientes wires
	**/
	Mux8x1 mux8x1(I, S, Q);
	Testbench_Mux8x1 signals_generator(I, S, Q);

endmodule

Mux8x1/Mux8x1.vcd
$date
	Thu Feb 25 01:46:42 2021
$end
$version
	Icarus Verilog
$end
$timescale
	1ns
$end
$scope module Probador $end
$var wire 3 ! S [2:0] $end
$var wire 4 " Q [3:0] $end
$var wire 32 # I [31:0] $end
$scope module mux8x1 $end
$var wire 4 $ c_arriba [3:0] $end
$var wire 4 % c_abajo [3:0] $end
$var wire 3 & S [2:0] $end
$var wire 4 ' Q [3:0] $end
$var wire 32 ( I [31:0] $end
$scope module mux_abajo $end
$var wire 16 ) I [15:0] $end
$var wire 2 * S [1:0] $end
$var wire 4 + c_arriba [3:0] $end
$var wire 4 , c_abajo [3:0] $end
$var wire 4 - Q [3:0] $end
$scope module mux_abajo $end
$var wire 8 . I [7:0] $end
$var wire 1 / S $end
$var wire 4 0 Q [3:0] $end
$upscope $end
$scope module mux_arriba $end
$var wire 8 1 I [7:0] $end
$var wire 1 2 S $end
$var wire 4 3 Q [3:0] $end
$upscope $end
$scope module mux_final $end
$var wire 8 4 I [7:0] $end
$var wire 1 5 S $end
$var wire 4 6 Q [3:0] $end
$upscope $end
$upscope $end
$scope module mux_arriba $end
$var wire 16 7 I [15:0] $end
$var wire 2 8 S [1:0] $end
$var wire 4 9 c_arriba [3:0] $end
$var wire 4 : c_abajo [3:0] $end
$var wire 4 ; Q [3:0] $end
$scope module mux_abajo $end
$var wire 8 < I [7:0] $end
$var wire 1 = S $end
$var wire 4 > Q [3:0] $end
$upscope $end
$scope module mux_arriba $end
$var wire 8 ? I [7:0] $end
$var wire 1 @ S $end
$var wire 4 A Q [3:0] $end
$upscope $end
$scope module mux_final $end
$var wire 8 B I [7:0] $end
$var wire 1 C S $end
$var wire 4 D Q [3:0] $end
$upscope $end
$upscope $end
$scope module mux_final $end
$var wire 8 E I [7:0] $end
$var wire 1 F S $end
$var wire 4 G Q [3:0] $end
$upscope $end
$upscope $end
$scope module signals_generator $end
$var wire 4 H Q [3:0] $end
$var reg 32 I I [31:0] $end
$var reg 3 J S [2:0] $end
$upscope $end
$upscope $end
$enddefinitions $end
#0
$dumpvars
bx J
b1110110010101000011001000010000 I
b0xxx H
b0xxx G
xF
b1xx00xx E
b0xx D
xC
b1x000x B
b0x A
x@
b10000 ?
b1x >
x=
b110010 <
b0xx ;
b1x :
b0x 9
bx 8
b11001000010000 7
b1xx 6
x5
b11x010x 4
b10x 3
x2
b1010100 1
b11x 0
x/
b1110110 .
b1xx -
b11x ,
b10x +
bx *
b111011001010100 )
b1110110010101000011001000010000 (
b0xxx '
bx &
b1xx %
b0xx $
b1110110010101000011001000010000 #
b0xxx "
bx !
$end
#1
b100 +
b100 3
b1100100 4
b110 ,
b110 0
b100 %
b100 -
b100 6
b0 9
b0 A
b100000 B
b10 :
b10 >
b1000000 E
b0 $
b0 ;
b0 D
02
0/
05
0@
0=
0C
b0 "
b0 '
b0 G
b0 H
b0 *
b0 8
0F
b0 !
b0 &
b0 J
#2
b1 "
b1 '
b1 G
b1 H
b101 %
b101 -
b101 6
b1010001 E
b1 $
b1 ;
b1 D
b101 +
b101 3
b1110101 4
b111 ,
b111 0
b1 9
b1 A
b110001 B
b11 :
b11 >
12
1/
1@
1=
b1 *
b1 8
b1 !
b1 &
b1 J
#3
b10 "
b10 '
b10 G
b10 H
b100 +
b100 3
b1100100 4
b110 ,
b110 0
b110 %
b110 -
b110 6
b0 9
b0 A
b100000 B
b10 :
b10 >
b1100010 E
b10 $
b10 ;
b10 D
02
0/
15
0@
0=
1C
b10 *
b10 8
b10 !
b10 &
b10 J
#4
b11 "
b11 '
b11 G
b11 H
b111 %
b111 -
b111 6
b1110011 E
b11 $
b11 ;
b11 D
b101 +
b101 3
b1110101 4
b111 ,
b111 0
b1 9
b1 A
b110001 B
b11 :
b11 >
12
1/
1@
1=
b11 *
b11 8
b11 !
b11 &
b11 J
#5
b100 +
b100 3
b1100100 4
b110 ,
b110 0
b100 %
b100 -
b100 6
b0 9
b0 A
b100000 B
b10 :
b10 >
b1000000 E
b0 $
b0 ;
b0 D
02
0/
05
0@
0=
0C
b100 "
b100 '
b100 G
b100 H
b0 *
b0 8
1F
b100 !
b100 &
b100 J
#6
b101 "
b101 '
b101 G
b101 H
b101 %
b101 -
b101 6
b1010001 E
b1 $
b1 ;
b1 D
b101 +
b101 3
b1110101 4
b111 ,
b111 0
b1 9
b1 A
b110001 B
b11 :
b11 >
12
1/
1@
1=
b1 *
b1 8
b101 !
b101 &
b101 J
#7
b110 "
b110 '
b110 G
b110 H
b100 +
b100 3
b1100100 4
b110 ,
b110 0
b110 %
b110 -
b110 6
b0 9
b0 A
b100000 B
b10 :
b10 >
b1100010 E
b10 $
b10 ;
b10 D
02
0/
15
0@
0=
1C
b10 *
b10 8
b110 !
b110 &
b110 J
#8
b111 "
b111 '
b111 G
b111 H
b111 %
b111 -
b111 6
b1110011 E
b11 $
b11 ;
b11 D
b101 +
b101 3
b1110101 4
b111 ,
b111 0
b1 9
b1 A
b110001 B
b11 :
b11 >
12
1/
1@
1=
b11 *
b11 8
b111 !
b111 &
b111 J
