Comparador/Testbench_Comparador.v
/* *************************************************************************
								Proyecto de Verilog
							Universidad de Costa Rica
						Escuela de Ingenieria Electrica
						IE-0323: Circuitos Digitales I 
							
								Testbench_Comparador.v
								
Autores: Jafet David Gutierrez Guevara <jafet.gutierrez@ucr.ac.cr>
        Carne: B73558
		 Pablo Daniel Brenes Segura <pablo.brenessegura@ucr.ac.cr>
        Carne: B51243
Fecha: 25/02/2021

Descripcion:
	Contiene testbench para el modulo del Comparador de Fechas. 
	El cual hace al modulo del comparador pasar por ciertas pruebas 
	para comprobar su funcionamiento.
	
***************************************************************************/
/** Se define una esacala de tiempo para definir lo que cada #1
 significa a la hora de simular el programa de la siguiente manera: 
 <Unidad de tiempo>/<Precision> 
 **/ 
`timescale 1ns/1ns
/** 
* El siguiente modulo es el modulo principal del testbench en el cual se 
* le aplican las pruebas pertinentes al modulo Comparador. 
 **/ 
module Testbench_Comparador(
	/** 
	* Tiene como salidas las entradas del modulo comparador. 
	* el dia y mes que entran del modulo registro y los de referencia. 
	**/ 
	output reg [4:0] dia, diaRef,
	output reg [3:0] mes, mesRef,
	/**
	*  Tiene como entradas las salidas del modulo comparador. 
	* la salida V del modulo comparador diciendo si el producto es 
	* vigente, vencido o no valido. 
	**/ 
	input wire [1:0] V);	
	
	/** 
	* Se abre un bloque initial para realizar algunas simulaciones 
	* Secuenciales dentro de el. 
	**/ 
	initial
	/** 
	*  Como se van a realizar varias pruebas se necesita inicial un bloque 
	* begin/end
	**/ 
		begin
			/**
			* Se crea un archivo tipo dump "Comparador.vcd" en el 
			* cual se van a guardar los cambios en los valores que se le hacen 
			* al archivo en  la simulacion. vcd por sus siglas en ingles value change dump. 
			**/
			$dumpfile("Comparador.vcd");
			/** 
			* Se usa dumpvars para especificar cuales variables se van a guardar 
			* en el archivo dump, como se declara sin argumento, se guardan todas.
			**/ 
			$dumpvars;

			/** 
			* Pruebas para el testbench del Comparador de Fechas. 
			**/ 

			//Prueba 1 - Todos los bits en 1
			#1
			dia = 5'b11111;
			mes = 4'b1111;
			diaRef = 5'b10110; 
			mesRef = 4'b0010;

			//Prueba 2 - Todos los bits en 0
			#1
			dia = 5'b00000;
			mes = 4'b0000;
			diaRef = 5'b10110; 
			mesRef = 4'b0010; 

			//Prueba 3- Una fecha invalida - 30 de febrero
			#1
			dia = 5'b11110;
			mes = 4'b0010;
			diaRef = 5'b10110; 
			mesRef = 4'b0010;

			//Prueba 4 - Una fecha invalida - 31 de junio
			#1
			dia = 5'b11111;
			mes = 4'b0110;
			diaRef = 5'b10110; 
			mesRef = 4'b0010;

			//Prueba 5 - Una fecha invalida - 5 del mes 14
			#1
			dia = 5'b00101;
			mes = 4'b1110;
			diaRef = 5'b10110; 
			mesRef = 4'b0010;

			//Prueba 6 - Una fecha invalida - 17 del mes 15
			#1
			dia = 5'b10001;
			mes = 4'b1111;
			diaRef = 5'b10110; 
			mesRef = 4'b0010;

			//Prueba 7 - Una fecha valida - 22 de febrero
			#1
			dia = 5'b10110;
			mes = 4'b0010;
			// fecha de referencia igual, vencido - 22 de febrero 
			diaRef = 5'b10110; 
			mesRef = 4'b0010;

			//Prueba 8 - Una fecha valida - 1 de enero
			#1
			dia = 5'b00001;
			mes = 4'b0001;
			// fecha de referencia, vencido -  16 de enero
			diaRef = 5'b10000; 
			mesRef = 4'b0001;

			//Prueba 9 - Una fecha valida - 14 de abril
			#1
			dia = 5'b01110;
			mes = 4'b0100;
			// Fecha de referencia vigente -  16 de enero
			diaRef = 5'b10000; 
			mesRef = 4'b0001;

			//Prueba 10 - Una fecha valida - 23 de febrero
			#1
			dia = 5'b10111;
			mes = 4'b0010;
			// Fecha de referencia vencida - 27 de julio
			diaRef = 5'b11011; 
			mesRef = 4'b0111;
			// Se termina la simulacion. 
			#1 $finish;
		end
endmodule

Comparador/Comparador.v
/* *************************************************************************
								Proyecto de Verilog
							Universidad de Costa Rica
						Escuela de Ingenieria Electrica
						IE-0323: Circuitos Digitales I 
							
								    Comparador.v
								 
Autores: Jafet David Gutierrez Guevara <jafet.gutierrez@ucr.ac.cr>
        Carné: B73558
		 Pablo Daniel Brenes Segura <pablo.brenessegura@ucr.ac.cr>
        Carné: B51243
Fecha: 25/02/2021

Descripcion:
	Contiene el modulo de un Comparador de Fechas, que recibe la fecha de 
    caducidad de un producto y basado en una fecha de referencia indica
    si el producto esta vencido, vigente o si la fecha recibida es invalida
    ya que los valores de entrada pueden dar fechas que no existen en el año 2021.
	
***************************************************************************/
/** Modulo de comparador en el cual se evaluan los casos invalidos de las fechas cada uno 
* por separado y se le asigna un valor de V de 00 en caso de que sea invalido 
* Despues se evaluan los casos validos y se comparan con la fecha de referenica
* para ver si el producto esta vencido o no. 
**/ 
module Comparador(
    // Se crea un un cable de entrada de 5 bits para el dia que se lee y el dia de referencia. 
    input wire [4:0] dia, diaRef,
    // Se crea un un cable de entrada de 4 bits para el mes que se lee y el mes de referencia. 
    input wire [3:0] mes, mesRef,
    /** Se tiene una salida tipo registro  de 2 bits ya que guarda la
    * informacion de si la fecha es invalida, vencida o vigente. 
    **/ 
    output reg [1:0] V);

    /** 
    * Se inicial un bloque always el cual ejecuta su contenido cada vez que hay un cambio
    * para esto es el asterisco '*' que se encuentra dentro de los parentesis. 
    **/ 
    always @(*) begin
        /** 
        * Se inicia un casez evaluando el mes y el dia que entran desde el registro. 
        * Se usa un casez debido a que se pueden ignorar algunos de los bits en algunos de los casos. 
        **/ 
        casez ({mes, dia})

        /**
        * Se verifican los casos en los que si el mes es febrero, 
        * no hayan dias 29, 30 ni 31. 
        **/ 
            9'b001011101: V <= 0;
            9'b00101111?: V <= 0;

        // Se verifica el caso en el que el mes sea cero.  
            9'b0000?????: V <= 0; 

        // Se verifica el caso en el que el dia sea cero.
            9'b????00000: V <= 0;
        /**
        * Se verifican los casos de los meses que no tienen 31 dias.
        * Por lo que hay que descartar los dias 31 de 4 meses.  
        **/ 
        //Caso en el que el mes no tenga 31 dias 
            9'b010011111: V <= 0;
            9'b011011111: V <= 0;
            9'b100111111: V <= 0;
            9'b101111111: V <= 0;

        /**
        * ya que se usan 4 bits para describir los meses, se tiene que 
        * Descartar los meses del 13 al 15 que no existen.
        **/ 
             9'b1101?????: V <= 0;
             9'b1110?????: V <= 0;
             9'b1111?????: V <= 0;

            // Se establece un caso default en caso de que ninguno de los casos anteriores se haya cumplido. 
            default: 
            // Se usa un bloque begin/end para inlcuir un if dentro. 
            begin
                /**
                * Con un if se comparan el dia y el mes de referencia 
                * con el dia y el mes que entran al modulo. 
                * Tal que si se cumple que el mes de referenia es mayor que el mes
                * del producto entonces se le asigna un valor de 01 a V (vencido). 
                * O si el mes de refencia es igual al mes de entrada pero el dia de refencia es mayor o igual. 
                * En caso de que no se cumpla ninguna de estas dos condiciones entonces se le asigna un valor de 
                * 10 a V (vigente). 
                **/ 
                if( (mes < mesRef) | (mes == mesRef) & (dia <= diaRef) ) V = 01; 
                else V = 10; 
            end
        endcase
    end
endmodule

Comparador/Probador_Comparador.v
/** Includes 
* Se tienen que incluir los archivos del programa principal
* y el del testbench del programa donde se simula
**/ 
`include "Comparador.v"
`include "Testbench_Comparador.v"
/** 
* En el modulo del probador se declaran los cables de las entradas 
* y salidas del programa. Y se llaman los modulos del testbench 
* y el comparador y se les asignan valores.
**/ 
module Probador();
/** 
	* Se declaran los wires que van a conectar cada una de las entradas
	* y salidas entre el modulo Comparador y su testbench
**/
 
	wire [4:0] dia, diaRef;

    wire [3:0] mes, mesRef;

    wire [1:0] V;
/**
* Se instancia el modulo del comparador del archivo "Comparador.v" y
* se le asignan los valores declarados en el testbench. 
**/
Comparador comparador(.dia(dia), .diaRef(diaRef), .mes(mes), .mesRef(mesRef), .V(V));
/**
* Se llama al modulo del Testbench del archivo "Testbench_Comparador.v" y
* se le asignan los valores declarados en el testbench. 
**/
Testbench_Comparador signals_generator(.dia(dia), .diaRef(diaRef), .mes(mes), .mesRef(mesRef), .V(V));

endmodule

Comparador/Comparador.vcd
$date
	Thu Feb 25 01:50:03 2021
$end
$version
	Icarus Verilog
$end
$timescale
	1ns
$end
$scope module Probador $end
$var wire 4 ! mesRef [3:0] $end
$var wire 4 " mes [3:0] $end
$var wire 5 # diaRef [4:0] $end
$var wire 5 $ dia [4:0] $end
$var wire 2 % V [1:0] $end
$scope module comparador $end
$var wire 4 & mesRef [3:0] $end
$var wire 4 ' mes [3:0] $end
$var wire 5 ( diaRef [4:0] $end
$var wire 5 ) dia [4:0] $end
$var reg 2 * V [1:0] $end
$upscope $end
$scope module signals_generator $end
$var wire 2 + V [1:0] $end
$var reg 5 , dia [4:0] $end
$var reg 5 - diaRef [4:0] $end
$var reg 4 . mes [3:0] $end
$var reg 4 / mesRef [3:0] $end
$upscope $end
$upscope $end
$enddefinitions $end
#0
$dumpvars
b10 /
bx .
b10110 -
bx ,
b10 +
b10 *
bx )
b10110 (
bx '
b10 &
b10 %
bx $
b10110 #
bx "
b10 !
$end
#1
b0 %
b0 *
b0 +
b1111 "
b1111 '
b1111 .
b11111 $
b11111 )
b11111 ,
#2
b0 "
b0 '
b0 .
b0 $
b0 )
b0 ,
#3
b10 "
b10 '
b10 .
b11110 $
b11110 )
b11110 ,
#4
b110 "
b110 '
b110 .
b11111 $
b11111 )
b11111 ,
#5
b1110 "
b1110 '
b1110 .
b101 $
b101 )
b101 ,
#6
b1111 "
b1111 '
b1111 .
b10001 $
b10001 )
b10001 ,
#7
b1 %
b1 *
b1 +
b10 "
b10 '
b10 .
b10110 $
b10110 )
b10110 ,
#8
b1 "
b1 '
b1 .
b1 $
b1 )
b1 ,
#9
b10 %
b10 *
b10 +
b100 "
b100 '
b100 .
b1110 $
b1110 )
b1110 ,
#10
b10 "
b10 '
b10 .
b10111 $
b10111 )
b10111 ,
