Registro/Testbench_Registro.v
/* *************************************************************************
								Proyecto de Verilog
							Universidad de Costa Rica
						Escuela de Ingenieria Electrica
						IE-0323: Circuitos Digitales I 
							
								Testbench_Registro.v
								
Autores: Jafet David Gutierrez Guevara <jafet.gutierrez@ucr.ac.cr>
        Carne: B73558
		 Pablo Daniel Brenes Segura <pablo.brenessegura@ucr.ac.cr>
        Carne: B51243
Fecha: 25/02/2021

Descripcion:
	Contiene testbench para el modulo del Registro Tipo D transparente. 
	El cual hace al modulo del Registro pasar por ciertas pruebas 
	para comprobar su funcionamiento.
	
***************************************************************************/
/** Se define una esacala de tiempo para definir lo que cada #1
 significa a la hora de simular el programa de la siguiente manera: 
 <Unidad de tiempo>/<Precision> 
 **/ 
`timescale 1ns/1ns
/** 
* El siguiente modulo es el modulo principal del testbench en el cual se 
* le aplican las pruebas pertinentes al modulo Registro. 
 **/ 
module tb_Registro (
    /** 
	* Tiene como salidas las entradas del modulo registro. 
	* El bus de 12 bits L, la entrada de clock CLK, la entrada de
    * reset clr y la entrada enable.  
	**/ 
    output reg [11:0] L, 
    output reg clk,
    output reg clr,
    output reg  en,
    /**
	*  Tiene como entradas las salidas del modulo registro. 
	* La salida Q en la que pasa los 12 bits del bus L. 
	**/ 
    input wire [11:0] Q
);
    /** 
    * Defino los estados iniciales de las variables CLR, CLK y EN. 
    * tal que el clock empiece en bajo, el clr desactivado y en en cero. 
    **/
    initial begin
        clk = 0; 
        clr = 1;
        en = 0;
    end

    /**
    * Defino un always que define que siempre que pasa un ciclo de tiempo
    * de reloj se pasa a cero. 
    **/ 
    always #1 clk = ~clk; 

	
	/** 
	* Se abre un bloque initial para realizar algunas simulaciones 
	* Secuenciales dentro de el. 
	**/ 
    initial 
    /** 
	*  Como se van a realizar varias pruebas se necesita inicial un bloque 
	* begin/end
	**/ 
        begin
			/**
			* Se crea un archivo tipo dump "Comparador.vcd" en el 
			* cual se van a guardar los cambios en los valores que se le hacen 
			* al archivo en  la simulacion. vcd por sus siglas en ingles value change dump. 
			**/
            $dumpfile("registro.vcd");
			/** 
			* Se usa dumpvars para especificar cuales variables se van a guardar 
			* en el archivo dump, como se declara sin argumento, se guardan todas.
			**/ 
            $dumpvars; 

            /** Prueba 1- 
            * Se prueba cuando se define primero el CLR ( en bajo), 
            * luego el enable ( en alto ) y despues L con un valor de la tabla 
            * para los cichles los cuales vencen el 1 de agosto. 
            **/

            #1 clr = 0; 
            #1 en = 1;
            #1 L = 12'b000011000100; 

            /**
            * Se vuelve a poner el valor de clr en alto y el valor de enable en cero. 
            **/ 
            #1 clr = 1;
            #1 en = 0; 
            /** Prueba 2- 
            * Se prueba cuando se define primero el clr en bajo, luego L y luego enable
            con valor de L de la tabla de Atun con fecha de 26 de febrero. 
            **/
            #1 clr = 0; 
            #1 L = 12'b110100010001; 
            #1 en = 1; 


            /**
            * Se vuelve a poner el valor de clr en alto y el valor de enable en cero. 
            **/
            #1 clr = 1;
            #1 en = 0; 
            /** Prueba 3- 
            * Se prueba cuando se define primero Enable, luego un valor 
            * de L para huevos segun la tabla de precios. Y por ultimo
            *  clear. 
            **/
            #1 en = 1; 
            #1 L = 12'b011110010101; 
            #2 clr = 0;
            // Se termina la simulacion. 
            #5 $finish;
        end
endmodule

Registro/Registro.v
/* *************************************************************************
								Proyecto de Verilog
							Universidad de Costa Rica
						Escuela de Ingenieria Electrica
						IE-0323: Circuitos Digitales I 
							
									Registro.v
								
Autores: Jafet David Gutierrez Guevara <jafet.gutierrez@ucr.ac.cr>
        Carné: B73558
		 Pablo Daniel Brenes Segura <pablo.brenessegura@ucr.ac.cr>
        Carné: B51243
Fecha: 25/02/2021

Descripcion:
	Contiene un modulo de Flip-Flop tipo D activado por flanco positivo con entrada de Clear, Enable y Clock. 
    Luego usando 12 veces este modulo para leer cada bit de la entrada del codigo de barras se hace un registro 
    para que lea cada bit por separado. 
	
***************************************************************************/
/**
* Registor tipo D transparente disparado por flanco creciente 
* Con reset asincronico disparado por flanco creciente y enable 
*
**/
module FF_D (
    input wire D, 
    input wire clr, 
    input wire en, 
    input wire clk,
    output reg   Q
);
 // Siempre que se encuentre un flanco positivo de la señal clk ejecuta lo que tiene dentro. 
    always@(posedge clk) 
        begin 
            // Si la entrada activada en bajo clr esta en bajo entonces transmite un valor de 0 a Q. 
            if(!clr) Q <= 0;
            /** Si no, entonces revisa la entrada de enable, 
            si esta en alto transmite el valor de entrada D a la salida Q. 
            */
            else if(en) Q <= D; 
            // Este caso es simplemente para que sea sintetizable. 
            else Q = Q;   
        end
endmodule
/** 
* Modulo de Registro llamando 12 veces al modulo de Flip Flop tipo D descrito. 
* Toma 12 bits de entrada y los transmite a una salida QR de 12 bits. 
**/ 
module Registro (
    input wire [11:0] L, 
    input wire CLK, 
    input wire  CLR,
    input wire EN, 
    output wire [11:0] QR 
);
    // Bits correspondientes al dia. 
    FF_D bit0( .D(L[0]), .clr(CLR), .clk(CLK), .en(EN), .Q(QR[0]) );
    FF_D bit1( .D(L[1]), .clr(CLR), .clk(CLK), .en(EN), .Q(QR[1]) );
    FF_D bit2( .D(L[2]), .clr(CLR), .clk(CLK), .en(EN), .Q(QR[2]) );
    FF_D bit3( .D(L[3]), .clr(CLR), .clk(CLK), .en(EN), .Q(QR[3]) );
    FF_D bit4( .D(L[4]), .clr(CLR), .clk(CLK), .en(EN), .Q(QR[4]) );
    //Bits correspondientes al mes 
    FF_D bit5( .D(L[5]), .clr(CLR), .clk(CLK), .en(EN), .Q(QR[5]) );
    FF_D bit6( .D(L[6]), .clr(CLR), .clk(CLK), .en(EN), .Q(QR[6]) );
    FF_D bit7( .D(L[7]), .clr(CLR), .clk(CLK), .en(EN), .Q(QR[7]) );
    FF_D bit8( .D(L[8]), .clr(CLR), .clk(CLK), .en(EN), .Q(QR[8]) );
    // Bits correspondientes al codigo del producto.
    FF_D bit9( .D(L[9]), .clr(CLR), .clk(CLK), .en(EN), .Q(QR[9]) );
    FF_D bit10( .D(L[10]), .clr(CLR), .clk(CLK), .en(EN), .Q(QR[10]) );
    FF_D bit11( .D(L[11]), .clr(CLR), .clk(CLK), .en(EN), .Q(QR[11]) );

endmodule

Registro/Probador_Registro.v
/** Includes 
* Se tienen que incluir los archivos del programa principal
* y el del testbench del programa donde se simula
**/ 
`include "Registro.v"
`include "Testbench_Registro.v"
/** 
* En el modulo del probador se declaran los cables de las entradas 
* y salidas del programa. Y se llaman los modulos del testbench 
* y el registro y se les asignan valores.
**/ 
module probador ();
	/** 
	* Se declaran los wires que van a conectar cada una de las entradas
	* y salidas entre el modulo Registro y su testbench
	**/
    wire [11:0] L, QR; 
    wire CLK;
    wire CLR; 
    wire EN; 
/**
* Se instancia el modulo del registro del archivo "Registro.v" y
* se le asignan los valores declarados en el testbench. 
**/
Registro registrofinal( .L(L), .QR(QR), .CLR(CLR), .CLK(CLK), .EN(EN)  );
/**
* Se instancia el modulo del Testbench del archivo "Testbench_Registro.v" y
* se le asignan los valores declarados en el testbench. 
**/
tb_Registro signals_generator( .L(L), .Q(QR), .clr(CLR), .clk(CLK), .en(EN)  );
endmodule

Registro/Registro.vcd
$date
	Thu Feb 25 02:31:33 2021
$end
$version
	Icarus Verilog
$end
$timescale
	1ns
$end
$scope module probador $end
$var wire 12 ! QR [11:0] $end
$var wire 12 " L [11:0] $end
$var wire 1 # EN $end
$var wire 1 $ CLR $end
$var wire 1 % CLK $end
$scope module registrofinal $end
$var wire 12 & QR [11:0] $end
$var wire 12 ' L [11:0] $end
$var wire 1 # EN $end
$var wire 1 $ CLR $end
$var wire 1 % CLK $end
$scope module bit0 $end
$var wire 1 ( D $end
$var wire 1 # en $end
$var wire 1 $ clr $end
$var wire 1 % clk $end
$var reg 1 ) Q $end
$upscope $end
$scope module bit1 $end
$var wire 1 * D $end
$var wire 1 # en $end
$var wire 1 $ clr $end
$var wire 1 % clk $end
$var reg 1 + Q $end
$upscope $end
$scope module bit10 $end
$var wire 1 , D $end
$var wire 1 # en $end
$var wire 1 $ clr $end
$var wire 1 % clk $end
$var reg 1 - Q $end
$upscope $end
$scope module bit11 $end
$var wire 1 . D $end
$var wire 1 # en $end
$var wire 1 $ clr $end
$var wire 1 % clk $end
$var reg 1 / Q $end
$upscope $end
$scope module bit2 $end
$var wire 1 0 D $end
$var wire 1 # en $end
$var wire 1 $ clr $end
$var wire 1 % clk $end
$var reg 1 1 Q $end
$upscope $end
$scope module bit3 $end
$var wire 1 2 D $end
$var wire 1 # en $end
$var wire 1 $ clr $end
$var wire 1 % clk $end
$var reg 1 3 Q $end
$upscope $end
$scope module bit4 $end
$var wire 1 4 D $end
$var wire 1 # en $end
$var wire 1 $ clr $end
$var wire 1 % clk $end
$var reg 1 5 Q $end
$upscope $end
$scope module bit5 $end
$var wire 1 6 D $end
$var wire 1 # en $end
$var wire 1 $ clr $end
$var wire 1 % clk $end
$var reg 1 7 Q $end
$upscope $end
$scope module bit6 $end
$var wire 1 8 D $end
$var wire 1 # en $end
$var wire 1 $ clr $end
$var wire 1 % clk $end
$var reg 1 9 Q $end
$upscope $end
$scope module bit7 $end
$var wire 1 : D $end
$var wire 1 # en $end
$var wire 1 $ clr $end
$var wire 1 % clk $end
$var reg 1 ; Q $end
$upscope $end
$scope module bit8 $end
$var wire 1 < D $end
$var wire 1 # en $end
$var wire 1 $ clr $end
$var wire 1 % clk $end
$var reg 1 = Q $end
$upscope $end
$scope module bit9 $end
$var wire 1 > D $end
$var wire 1 # en $end
$var wire 1 $ clr $end
$var wire 1 % clk $end
$var reg 1 ? Q $end
$upscope $end
$upscope $end
$scope module signals_generator $end
$var wire 12 @ Q [11:0] $end
$var reg 12 A L [11:0] $end
$var reg 1 % clk $end
$var reg 1 $ clr $end
$var reg 1 # en $end
$upscope $end
$upscope $end
$enddefinitions $end
#0
$dumpvars
bx A
bx @
x?
x>
x=
x<
x;
x:
x9
x8
x7
x6
x5
x4
x3
x2
x1
x0
x/
x.
x-
x,
x+
x*
x)
x(
bx '
bx &
0%
1$
0#
bx "
bx !
$end
#1
0)
0+
01
03
05
07
09
0;
0=
0?
0-
b0 !
b0 &
b0 @
0/
0$
1%
#2
1#
0%
#3
0.
1,
1>
1<
0:
08
16
04
02
10
0*
0(
b11100100100 "
b11100100100 '
b11100100100 A
1%
#4
0#
1$
0%
#5
0$
1%
#6
0,
0>
0<
1:
06
12
00
1(
b10001001 "
b10001001 '
b10001001 A
0%
#7
1#
1%
#8
0#
1$
0%
#9
1)
13
b10001001 !
b10001001 &
b10001001 @
1;
1#
1%
#10
1.
1>
1<
0:
14
02
10
1*
b101100010111 "
b101100010111 '
b101100010111 A
0%
#11
0;
03
b0 !
b0 &
b0 @
0)
0$
1%
